client/README.md
client/README_FILE_MEMORY.md
client/README_GITHUB_WORKFLOWS.md
client/__init__.py
client/cli.py
client/file_memory_api.py
client/file_memory_client.py
client/github_workflow_generator.py
client/runner.py
client/terminal.py
core/__init__.py
core/ai.py
core/chat_processor.py
core/code_engineer.py
core/comment_formatter.py
core/decision.py
core/diff.py
core/file_fetcher.py
core/file_memory.py
core/file_selector.py
core/git_manager.py
core/log_config.py
core/log_manager.py
core/prompt_generator.py
core/version_manager.py
core/workflow_engine.py
bella_issues_bot-0.1.24.dist-info/LICENSE.md
bella_issues_bot-0.1.24.dist-info/METADATA
bella_issues_bot-0.1.24.dist-info/WHEEL
bella_issues_bot-0.1.24.dist-info/entry_points.txt
bella_issues_bot-0.1.24.dist-info/RECORD
