Metadata-Version: 2.1
Name: bella-issues-bot
Version: 0.1.24
Summary: bella-issues-bot 是一个基于人工智能的多功能代码开发助手，具备两种强大的工作模式：个人开发助手模式：在日常开发过程中，作为命令行工具辅助编码，帮助分析代码、生成实现、解决技术难题。GitHub自动化模式：集成到GitHub工作流中，自动监控和处理项目Issues，无需人工干预即可分析需求、提出解决方案并实现代码变更。
Home-page: https://github.com/szl97/bella-issues-bot
License: MIT
Author: saizhuolin
Requires-Python: >=3.10,<3.13
Classifier: Development Status :: 4 - Beta
Classifier: License :: OSI Approved :: MIT License
Classifier: Programming Language :: Python :: 3
Classifier: Programming Language :: Python :: 3.10
Classifier: Programming Language :: Python :: 3.11
Classifier: Topic :: Scientific/Engineering :: Artificial Intelligence
Requires-Dist: PyGithub (>=2.1.1,<3.0.0)
Requires-Dist: argparse (>=1.4.0)
Requires-Dist: colorama (>=0.4.4)
Requires-Dist: colorlog (>=6.8.0,<7.0.0)
Requires-Dist: gitpython (>=3.1.40,<4.0.0)
Requires-Dist: jinja2 (>=3.1.0,<4.0.0)
Requires-Dist: langchain (>=0.3.0,<0.4.0)
Requires-Dist: langchain-community (>=0.3.0,<0.4.0)
Requires-Dist: langchain-core (>=0.3.0,<0.4.0)
Requires-Dist: langchain-openai (>=0.1.0)
Requires-Dist: openai (>=1.3.5,<2.0.0)
Requires-Dist: pathspec (>=0.9.0)
Requires-Dist: pydantic (>=2.5.0,<3.0.0)
Requires-Dist: pytest (>=7.4.0,<8.0.0)
Requires-Dist: python-dotenv (>=1.0.0,<2.0.0)
Requires-Dist: pyyaml (>=6.0)
Requires-Dist: toml (>=0.10.2)
Requires-Dist: typing-extensions (>=4.0.0)
Project-URL: Documentation, https://github.com/szl97/bella-issues-bot
Project-URL: Repository, https://github.com/szl97/bella-issues-bot
